{
    "name": "Build Your Own Mechanical Keyboard Kit",
    "id": "diy-keyboard",
    "categories": [
        9,
        6,
        5,
        2
    ],
    "organizations": [
        "Painless Prototyping"
    ],
    "locations": [
        "Massachusetts"
    ],
    "headline": "",
    "description": "Kit for learning how to solder and write code. Users create their own mechanical keyboard that does exactly what they want it to do.",
    "start_date": "2020-07-16",
    "end_date": "Ongoing",
    "skills": [
        3,
        8,
        9,
        10,
        20,
        23,
        24
    ],
    "images": [
        {
            "name": "Components",
            "src": "diy-keyboard/1.jpg"
        },
        {
            "name": "Assembling board",
            "src": "diy-keyboard/2.jpg"
        },
        {
            "name": "First working prototype",
            "src": "diy-keyboard/3.jpg"
        }
    ],
    "links": [
        {
            "name": "Working MVP",
            "src": "https://www.youtube.com/watch?v=LUBRBuLBB54"
        },
        {
            "name": "Product Page",
            "src": "https://painlessprototyping.com/buttonboardv2"
        }
    ],
    "preview_img": {
        "name": "First working prototype",
        "src": "diy-keyboard/thumbnail.jpg"
    }
}